django_better_repr/__init__.py
django_better_repr/apps.py
django_better_repr/bases.py
django_better_repr/config.py
django_better_repr/exceptions.py
django_better_repr/signals.py
django_better_repr-1.0.7.dist-info/LICENSE.txt
django_better_repr-1.0.7.dist-info/METADATA
django_better_repr-1.0.7.dist-info/WHEEL
django_better_repr-1.0.7.dist-info/top_level.txt
django_better_repr-1.0.7.dist-info/RECORD
