Metadata-Version: 2.1
Name: django-better-repr
Version: 1.0.7
Summary: Django model reprs for humans!
Home-page: https://github.com/MrSage/django-better-repr
Author: Collin Sage
Author-email: 3229549+MrSage@users.noreply.github.com
License: MIT
Project-URL: Documentation, https://github.com/MrSage/django-better-repr
Project-URL: Source, https://github.com/MrSage/django-better-repr
Project-URL: Download, https://pypi.org/project/django-better-repr/#files
Project-URL: Tracker, https://github.com/MrSage/django-better-repr/issues
Platform: any
Classifier: Development Status :: 5 - Production/Stable
Classifier: Programming Language :: Python
Classifier: Framework :: Django :: 4.2
Requires-Python: >=3.8
License-File: LICENSE.txt
Requires-Dist: django
Requires-Dist: importlib-metadata ; python_version < "3.8"
Provides-Extra: testing
Requires-Dist: setuptools ; extra == 'testing'
Requires-Dist: pytest ; extra == 'testing'
Requires-Dist: pytest-cov ; extra == 'testing'
Requires-Dist: pytest-django ; extra == 'testing'
